LICENSE
MANIFEST.in
README.md
setup.py
nikeplusapi/__init__.py
nikeplusapi/export.py
nikeplusapi.egg-info/PKG-INFO
nikeplusapi.egg-info/SOURCES.txt
nikeplusapi.egg-info/dependency_links.txt
nikeplusapi.egg-info/entry_points.txt
nikeplusapi.egg-info/top_level.txt