Metadata-Version: 1.1
Name: nikeplusapi
Version: 0.4.1
Summary: Export nikeplus data to CSV format
Home-page: https://github.com/durden/nikeplus
Author: Luke Lee
Author-email: durdenmisc@gmail.com
License: MIT
Platform: any
Classifier: Development Status :: 4 - Beta
Classifier: Environment :: Console
Classifier: Intended Audience :: Developers
Classifier: Intended Audience :: End Users/Desktop
Classifier: Natural Language :: English
Classifier: Operating System :: OS Independent
Classifier: Topic :: System :: Archiving
